flask_pay_wx/.DS_Store
flask_pay_wx/Const.py
flask_pay_wx/Manager.py
flask_pay_wx/MiniPayBean.py
flask_pay_wx/README.md
flask_pay_wx/__init__.py
flask_pay_wx/__pycache__/Const.cpython-37.pyc
flask_pay_wx/__pycache__/Manager.cpython-37.pyc
flask_pay_wx/__pycache__/MiniPayBean.cpython-37.pyc
flask_pay_wx/__pycache__/__init__.cpython-37.pyc
flask_pay_wx/utils/Util.py
flask_pay_wx/utils/__init__.py
flask_pay_wx/utils/__pycache__/Util.cpython-37.pyc
flask_pay_wx/utils/__pycache__/__init__.cpython-37.pyc
flask_pay_wx/v2/.DS_Store
flask_pay_wx/v2/Tools.py
flask_pay_wx/v2/__init__.py
flask_pay_wx/v2/__pycache__/Tools.cpython-37.pyc
flask_pay_wx/v2/__pycache__/__init__.cpython-37.pyc
flask_pay_wx/v2/mini/PayHelper.py
flask_pay_wx/v2/mini/__init__.py
flask_pay_wx/v2/mini/__pycache__/PayHelper.cpython-37.pyc
flask_pay_wx/v2/mini/__pycache__/__init__.cpython-37.pyc
flask_pay_wx/v3/.DS_Store
flask_pay_wx/v3/Tools.py
flask_pay_wx/v3/__init__.py
flask_pay_wx/v3/__pycache__/Tools.cpython-37.pyc
flask_pay_wx/v3/__pycache__/__init__.cpython-37.pyc
flask_pay_wx/v3/mini/PayHelper.py
flask_pay_wx/v3/mini/__init__.py
flask_pay_wx/v3/mini/__pycache__/PayHelper.cpython-37.pyc
flask_pay_wx/v3/mini/__pycache__/__init__.cpython-37.pyc
Flask_Pay_WX-1.0.5.dist-info/METADATA
Flask_Pay_WX-1.0.5.dist-info/WHEEL
Flask_Pay_WX-1.0.5.dist-info/top_level.txt
Flask_Pay_WX-1.0.5.dist-info/RECORD
