Metadata-Version: 2.1
Name: Flask-Pay-WX
Version: 1.0.5
Summary: attachment file
Home-page: http://iotwonderful.com
Author: lisichen, zhangchi
Author-email: UNKNOWN
License: BSD
Platform: any
Classifier: Environment :: Web Environment
Classifier: Intended Audience :: Developers
Classifier: License :: OSI Approved :: BSD License
Classifier: Operating System :: OS Independent
Classifier: Programming Language :: Python
Classifier: Programming Language :: Python :: 3.7
Classifier: Topic :: Internet :: WWW/HTTP :: Dynamic Content
Classifier: Topic :: Software Development :: Libraries :: Python Modules
Requires-Dist: Flask
Requires-Dist: xmltodict
Requires-Dist: requests
Requires-Dist: pycryptodome
Requires-Dist: cryptography
